cv_text_element/__init__.py
cv_text_element/example.py
cv_text_element/frontend/build/asset-manifest.json
cv_text_element/frontend/build/bootstrap.min.css
cv_text_element/frontend/build/bootstrap.min.css.map
cv_text_element/frontend/build/index.html
cv_text_element/frontend/build/static/css/main.5f9db33f.css
cv_text_element/frontend/build/static/css/main.5f9db33f.css.map
cv_text_element/frontend/build/static/js/main.108928b6.js
cv_text_element/frontend/build/static/js/main.108928b6.js.LICENSE.txt
cv_text_element/frontend/build/static/js/main.108928b6.js.map
text_component-0.0.1.dist-info/LICENSE
text_component-0.0.1.dist-info/METADATA
text_component-0.0.1.dist-info/WHEEL
text_component-0.0.1.dist-info/top_level.txt
text_component-0.0.1.dist-info/RECORD
